{
  "brand": "MaxFashion",
  "sector": "fashion",
  "occasion": "national_day",
  "product": "abaya collection",
  "intelligence": {
    "must_use": [
      {
        "pattern": "limited_time_offer",
        "as": "image",
        "engagement": 100,
        "obs": 3
      },
      {
        "pattern": "fashion_accessory_integration",
        "as": "image",
        "engagement": 83,
        "obs": 6
      },
      {
        "pattern": "winter_comfort_cozy",
        "as": "video",
        "engagement": 75,
        "obs": 4
      },
      {
        "pattern": "collab_post",
        "as": "image",
        "engagement": 75,
        "obs": 4
      },
      {
        "pattern": "cultural_identity_marker",
        "as": "image",
        "engagement": 75,
        "obs": 4
      }
    ],
    "never_use": [
      {
        "pattern": "occasion_playscultural_moment_tie_in",
        "as": "image",
        "engagement": 2,
        "obs": 63
      },
      {
        "pattern": "eid_family_gathering",
        "as": "image",
        "engagement": 0,
        "obs": 55
      },
      {
        "pattern": "eid_family_gathering",
        "as": "video",
        "engagement": 0,
        "obs": 30
      },
      {
        "pattern": "eid_family_gathering",
        "as": "carousel_slide",
        "engagement": 0,
        "obs": 12
      }
    ],
    "visual_dna": [
      {
        "lighting": "golden_hour",
        "setting": "outdoor",
        "total": 12,
        "high_pct": 75
      },
      {
        "lighting": "flat_bright",
        "setting": "retail_store",
        "total": 9,
        "high_pct": 56
      },
      {
        "lighting": "natural",
        "setting": "outdoor",
        "total": 52,
        "high_pct": 44
      }
    ],
    "winning_formulas": [
      {
        "content_type": "image",
        "pattern": "fashion_accessory_integration",
        "occasion": "evergreen",
        "total": 4,
        "high_pct": 100
      },
      {
        "content_type": "video",
        "pattern": "occasion_playscultural_moment_tie_in",
        "occasion": "ramadan",
        "total": 3,
        "high_pct": 100
      },
      {
        "content_type": "video",
        "pattern": "brand_collab",
        "occasion": "ramadan",
        "total": 5,
        "high_pct": 80
      }
    ],
    "universal": [
      {
        "rule": "ALWAYS use 'youth_culture_collab' — 100% high engagement across all sectors",
        "pattern": "youth_culture_collab",
        "engagement": 100,
        "obs": 10,
        "priority": "critical"
      },
      {
        "rule": "ALWAYS use 'heritage_storytelling_hook' — 93% high engagement across all sectors",
        "pattern": "heritage_storytelling_hook",
        "engagement": 93,
        "obs": 14,
        "priority": "high"
      },
      {
        "rule": "ALWAYS use 'overhead_tabletop_spread' — 88% high engagement across all sectors",
        "pattern": "overhead_tabletop_spread",
        "engagement": 88,
        "obs": 41,
        "priority": "high"
      }
    ],
    "occasion": {
      "occasion": "national_day",
      "engagement": 40,
      "obs": 30,
      "verdict": "use_selectively",
      "rule": "national_day: Use carefully (40%)"
    },
    "emotion": {
      "emotion": "anticipation",
      "engagement": 71,
      "obs": 14,
      "verdict": "use_actively"
    },
    "campaign_arc": {
      "opening_emotion": "pride",
      "peak_emotion": "pride",
      "closing_emotion": "warmth",
      "emotion_ranking": [
        {
          "emotion_primary": "pride",
          "pct": 28,
          "n": 18
        }
      ],
      "arc_description": "Start with pride (28%), build to pride, close with warmth/gratitude"
    },
    "obs_count": 258
  },
  "concept": "**1. CONCEPT NAME:**  \n\"فخر واحتضان - Pride & Embrace\"\n\n---\n\n**2. CONCEPT DESCRIPTION:**  \nThis campaign celebrates Saudi National Day by highlighting our heritage through a stunning new abaya collection. The idea is to evoke feelings of pride, warmth, and anticipation as we unveil how each piece represents elegance, comfort, and cultural significance.\n\n---\n\n**3. VISUAL WORLD:**  \nSet during the golden hour, the lighting is warm and inviting, creating a soft and ethereal glow over the models. The color palette incorporates rich jewel tones complemented by gold accents, with textures that are luxurious yet cozy — think flowing fabrics that capture movement. Outdoor settings, such as parks or traditional marketplaces, enhance the cultural connection, radiating community and unity.\n\n---\n\n**4. STORYBOARD:**\n\n- **Frame 1: [Opening hook — anticipation]**  \n  A close-up of intricate embroidery on an abaya, slowly zooming out to reveal a model's lively smile. Text overlay: “Embrace the spirit of National Day…”\n\n- **Frame 2: [Build tension]**  \n  A woman looks out over a scenic landscape, dressed in a beautifully draped abaya, as the sunset casts a golden hue. Soft ambient sounds of laughter and community celebration fill the background.\n\n- **Frame 3: [Hero moment — product/brand reveal]**  \n  The scene transitions to a group of diverse women in the new abaya collection, twirling joyfully and showcasing the comfort and elegance of each design against vibrant outdoor backdrops. Overlay text reads: “Unveil your pride with MaxFashion…”\n\n- **Frame 4: [Cultural connection — heritage/community]**  \n  Various shots of women in the collection engaging in traditional activities, like crafting or dancing, linking fashion with cultural heritage. Quick cuts highlight the craftsmanship behind each piece.\n\n- **Frame 5: [Close — call to action]**  \n  The camera pulls back to show a communal gathering with everyone wearing the abayas they selected, smiling and celebrating. Text overlay: “Visit our stores for a limited-time offer and join the celebration!”\n\n---\n\n**5. CAPTION:**  \n\"احتفلي باليوم الوطني بفخر! 🌟 مجموعة العبايات الجديدة من ماكس فاشن في انتظارك.  #فخر_واحتضان\"\n\n---\n\n**6. MOOD REFERENCE:**  \nThe look and feel are warm, vibrant, and celebratory, merging contemporary fashion with rich traditional elements to inspire a sense of unity and pride in heritage.",
  "chains": [
    "tf26_02",
    "tf26_01",
    "tf26_03"
  ],
  "timestamp": "2026-06-04T14:13:09.054704"
}