{
  "brand": "NiceOne",
  "sector": "beauty_personal_care",
  "occasion": "evergreen",
  "product": "skincare set",
  "intelligence": {
    "must_use": [],
    "never_use": [
      {
        "pattern": "arabic_caption",
        "as": "image",
        "engagement": 5,
        "obs": 44
      },
      {
        "pattern": "educational_content",
        "as": "carousel_slide",
        "engagement": 5,
        "obs": 41
      },
      {
        "pattern": "educational_content",
        "as": "video",
        "engagement": 5,
        "obs": 80
      },
      {
        "pattern": "brand_hashtag_promotion",
        "as": "image",
        "engagement": 4,
        "obs": 28
      },
      {
        "pattern": "tutorial_how_to",
        "as": "carousel_slide",
        "engagement": 3,
        "obs": 37
      }
    ],
    "visual_dna": [
      {
        "lighting": "mixed_ambient",
        "setting": "studio",
        "total": 5,
        "high_pct": 40
      },
      {
        "lighting": "warm_studio",
        "setting": "retail_store",
        "total": 5,
        "high_pct": 40
      },
      {
        "lighting": "warm_studio",
        "setting": "salon",
        "total": 28,
        "high_pct": 14
      }
    ],
    "winning_formulas": [],
    "universal": [
      {
        "rule": "ALWAYS use 'youth_culture_collab' — 100% high engagement across all sectors",
        "pattern": "youth_culture_collab",
        "engagement": 100,
        "obs": 10,
        "priority": "critical"
      },
      {
        "rule": "ALWAYS use 'heritage_storytelling_hook' — 93% high engagement across all sectors",
        "pattern": "heritage_storytelling_hook",
        "engagement": 93,
        "obs": 14,
        "priority": "high"
      },
      {
        "rule": "ALWAYS use 'overhead_tabletop_spread' — 88% high engagement across all sectors",
        "pattern": "overhead_tabletop_spread",
        "engagement": 88,
        "obs": 41,
        "priority": "high"
      }
    ],
    "occasion": {
      "occasion": "evergreen",
      "engagement": 31,
      "obs": 1293,
      "verdict": "use_selectively",
      "rule": "evergreen: Use carefully (31%)"
    },
    "emotion": {
      "emotion": "anticipation",
      "engagement": 33,
      "obs": 24,
      "verdict": "use_carefully"
    },
    "campaign_arc": {
      "opening_emotion": "anticipation",
      "peak_emotion": "warmth",
      "closing_emotion": "aspiration",
      "emotion_ranking": [
        {
          "emotion_primary": "anticipation",
          "pct": 48,
          "n": 128
        },
        {
          "emotion_primary": "warmth",
          "pct": 39,
          "n": 88
        },
        {
          "emotion_primary": "pride",
          "pct": 32,
          "n": 68
        },
        {
          "emotion_primary": "appetite",
          "pct": 28,
          "n": 431
        },
        {
          "emotion_primary": "urgency",
          "pct": 21,
          "n": 28
        },
        {
          "emotion_primary": "trust",
          "pct": 18,
          "n": 22
        },
        {
          "emotion_primary": "aspiration",
          "pct": 11,
          "n": 387
        }
      ],
      "arc_description": "Start with anticipation (48%), build to warmth, close with warmth/gratitude"
    },
    "obs_count": 320
  },
  "concept": "### 1. CONCEPT NAME \n*نضارة جميلة – Beautiful Radiance*\n\n### 2. CONCEPT DESCRIPTION \nThe concept captures the anticipation and emotional journey of discovering the transformative power of NiceOne's skincare set. It invites consumers to experience a unique blend of heritage and modern beauty through a visual narrative that builds warmth and gratitude.\n\n### 3. VISUAL WORLD \nThe visual world combines warm studio lighting with ambient tones, creating an inviting atmosphere. The color palette will feature soft pastels—peach, cream, and delicate greens—blended with natural textures like silk and linen. The mood will evoke a sense of comfort and intimacy, with a slight ethereal glow to emphasize the beauty and purity of the skincare products.\n\n### 4. STORYBOARD \n**Frame 1: [Opening hook — anticipation]**  \nA close-up of a hand gently touching a beautifully wrapped box, fingers lightly brushing against the soft, textured fabric. The camera lingers, building anticipation as a soft, melodic sound plays in the background.\n\n**Frame 2: [Build tension]**  \nVisuals of a woman in a serene environment, looking at her reflection with a hint of concern on her face. The lighting dims slightly, and her fingers dance around her skin, symbolizing her search for hydration and radiance.\n\n**Frame 3: [Hero moment — product/brand reveal]**  \nThe lights brighten, focusing on the NiceOne skincare set elegantly placed against a backdrop of rich textiles and delicate flowers. A voiceover states, \"Reveal your beautiful radiance, inside and out,\" as the camera captures the shine of the products.\n\n**Frame 4: [Cultural connection — heritage/community]**  \nCut to diverse women of different ages within a warm family setting, sharing beauty tips, laughter, and skincare secrets, highlighting the communal bond of beauty rituals passed down through generations with spices and natural ingredients. \n\n**Frame 5: [Close — call to action]**  \nThe screen pulls back to reveal the entire skincare range alongside a warm glow, with the tagline “Nourish your beauty journey” appearing. A call to action invites viewers to visit the NiceOne website, with the voiceover encouraging, \"Join the community today.\"\n\n### 5. CAPTION \n\"مرحبًا بك في عالم نضارة جميلة! حيث تبدأ رحلتك نحو بشرة مثالية مع لمسة من الود. 🌿✨\"\n\n### 6. MOOD REFERENCE \nThe look and feel should be intimate and inviting, combining the warmth of home with the luxury of a high-end spa, making the viewer feel both anticipated and cherished.",
  "chains": [
    "tf26_02",
    "tf26_01",
    "tf26_03"
  ],
  "timestamp": "2026-06-04T08:25:29.402093"
}