{
  "brand": "ROSHN",
  "sector": "real_estate",
  "occasion": "founding_day",
  "product": "luxury villa",
  "intelligence": {
    "must_use": [],
    "never_use": [
      {
        "pattern": "arabic_caption",
        "as": "video",
        "engagement": 5,
        "obs": 20
      },
      {
        "pattern": "location_tagged_riyadh",
        "as": "image",
        "engagement": 5,
        "obs": 21
      },
      {
        "pattern": "hashtag_restaurant_romantic",
        "as": "video",
        "engagement": 0,
        "obs": 9
      },
      {
        "pattern": "riyadh_location",
        "as": "video",
        "engagement": 0,
        "obs": 14
      },
      {
        "pattern": "sports_passion_peg",
        "as": "video",
        "engagement": 0,
        "obs": 9
      }
    ],
    "visual_dna": [
      {
        "lighting": "flat_bright",
        "setting": "office",
        "total": 6,
        "high_pct": 17
      },
      {
        "lighting": "natural",
        "setting": "outdoor",
        "total": 90,
        "high_pct": 2
      },
      {
        "lighting": "golden_hour",
        "setting": "outdoor",
        "total": 7,
        "high_pct": 0
      }
    ],
    "winning_formulas": [],
    "universal": [
      {
        "rule": "ALWAYS use 'youth_culture_collab' — 100% high engagement across all sectors",
        "pattern": "youth_culture_collab",
        "engagement": 100,
        "obs": 10,
        "priority": "critical"
      },
      {
        "rule": "ALWAYS use 'heritage_storytelling_hook' — 93% high engagement across all sectors",
        "pattern": "heritage_storytelling_hook",
        "engagement": 93,
        "obs": 14,
        "priority": "high"
      },
      {
        "rule": "ALWAYS use 'overhead_tabletop_spread' — 88% high engagement across all sectors",
        "pattern": "overhead_tabletop_spread",
        "engagement": 88,
        "obs": 41,
        "priority": "high"
      }
    ],
    "occasion": {
      "occasion": "founding_day",
      "engagement": 85,
      "obs": 13,
      "verdict": "invest_heavily",
      "rule": "founding_day: GO ALL IN (85%)"
    },
    "emotion": {
      "emotion": "aspiration",
      "engagement": 3,
      "obs": 70,
      "verdict": "avoid"
    },
    "campaign_arc": {
      "opening_emotion": "pride",
      "peak_emotion": "appetite",
      "closing_emotion": "warmth",
      "emotion_ranking": [
        {
          "emotion_primary": "pride",
          "pct": 89,
          "n": 9
        },
        {
          "emotion_primary": "appetite",
          "pct": 75,
          "n": 4
        }
      ],
      "arc_description": "Start with pride (89%), build to appetite, close with warmth/gratitude"
    },
    "obs_count": 113
  },
  "concept": "### 1. CONCEPT NAME \n\"أحيا الفخر | Living Pride\"\n\n### 2. CONCEPT DESCRIPTION \nCelebrate the spirit of Saudi founding day by showcasing the essence of luxury living in a ROSHN villa that embodies aspiration and pride. This campaign emphasizes a connection between contemporary luxury and traditional heritage to inspire potential homeowners to envision their future.\n\n### 3. VISUAL WORLD\nUtilize a flat-bright color palette emphasizing warm earth tones complemented by highlights of rich jewel colors to evoke luxury. The lighting will be soft yet luminous, reflecting warmth and elegance with textures such as polished marble, warm woods, and intricate traditional fabrics for a comforting yet upscale feel. The mood is aspirational with an underlying connection to cultural pride.\n\n### 4. STORYBOARD\n- **Frame 1: [Opening hook — aspiration]**\n  A panoramic view of a grand ROSHN villa at dawn, with the sun casting a soft glow. The camera slowly zooms into the villa, establishing a sense of luxury and elevation.\n\n- **Frame 2: [Build tension]**\n  Close-up shots of vibrant, happy families enjoying time together in beautifully designed spaces of the villa. The scene flows from the kitchen to the living room, showcasing modern elegance as a lively celebration unfolds.\n\n- **Frame 3: [Hero moment — product/brand reveal]**\n  A slow-motion reveal of the hero villa, with the camera panning across its stunning façade and an aerial view encompassing its lush surroundings, emphasizing the intricateness of its architectural design. \n\n- **Frame 4: [Cultural connection — heritage/community]**\n  Families engaging in traditional Saudi activities outside the villa, sharing laughter and food, against a backdrop of community and culture that ties the audience emotionally to the heritage celebration.\n\n- **Frame 5: [Close — call to action]**\n  Warm scenes of people leaving the villa as the sun sets, with a soft text overlay inviting potential buyers to \"Discover your legacy with ROSHN.\" A QR code appears leading to the website for more information.\n\n### 5. CAPTION \n\"في قلب الحلم السعودي، فيلاتنا تمثل فخرًنا ورفاهيتنا. انضموا إلينا في الاحتفال بتراثنا واستثمروا في مستقبلكم مع ROSHN!#يوم_التأسيس\"\n\n### 6. MOOD REFERENCE \nThe look and feel is a seamless blend of modern luxury and tradition, infused with warmth that evokes pride and connection, making each space feel like a cherished part of one’s heritage.",
  "chains": [
    "tf26_02",
    "tf26_01",
    "tf26_03"
  ],
  "timestamp": "2026-06-04T12:38:39.223210"
}