[
  {
    "shortcode": "Bsa9PvynYDE",
    "file": "01KS3CBX96S8AC5EGZQ89N5V8G.json",
    "error": "no_json"
  },
  {
    "shortcode": "yMKtMQHoNa",
    "file": "01KS3CBX99612N7DY2HY4JB3J9.json",
    "error": "no_json"
  },
  {
    "shortcode": "BRH20WtA2oh",
    "file": "01KS3CBX9BRBZ83WP3Q4E20AFS.json",
    "error": "no_json"
  },
  {
    "shortcode": "BPCZdXRDh8m",
    "file": "01KS3CBX9E5WS2H7ZVCX5XF23Z.json",
    "error": "no_json"
  },
  {
    "shortcode": "BlBKptRB9DV",
    "file": "01KS3CBX9G1PBCZXPFDQEWPGJG.json",
    "error": "no_json"
  },
  {
    "shortcode": "CJ3GhfXBesK",
    "file": "01KS3CBX9KAN7R8X8TW2FTVJEH.json",
    "error": "no_json"
  },
  {
    "shortcode": "B1uAqD9B6nh",
    "file": "01KS3CBX9PGAG0SA0GZ4178HPX.json",
    "error": "no_json"
  },
  {
    "shortcode": "C6ZEH2DK5FF",
    "file": "01KS3CBX9SDPJAHAMMRP0VNF8C.json",
    "error": "no_json"
  },
  {
    "shortcode": "C5i10MBKnvm",
    "file": "01KS3CBX9VW8YH5YT53KT1P2PV.json",
    "error": "no_json"
  },
  {
    "shortcode": "C5T1QB0K0FM",
    "file": "01KS3CBX9Y4XC7C7RJAC075TWT.json",
    "error": "no_json"
  },
  {
    "shortcode": "C5OqhNzq3TT",
    "file": "01KS3CBXA1Z3RAWR5TPQ8PMT38.json",
    "error": "no_json"
  },
  {
    "shortcode": "C5JEQR8K1do",
    "file": "01KS3CBXA3XN0Z9YSHX04TXSBA.json",
    "error": "no_json"
  },
  {
    "shortcode": "BGcdtj1noI3",
    "file": "01KS3CBXA607X0ESJHBNMMSP3G.json",
    "error": "no_json"
  },
  {
    "shortcode": "dzjspfnoDR",
    "file": "01KS3CBXA9WJ9YSG0N719DH6WV.json",
    "error": "no_json"
  },
  {
    "shortcode": "9ddb66noJ4",
    "file": "01KS3CBXACTDEX4WWQJHEG0ZM0.json",
    "error": "no_json"
  },
  {
    "shortcode": "ClyQNLlKsOn",
    "file": "01KS3CBXAEAS9MQE2JS72ZQ575.json",
    "error": "no_json"
  },
  {
    "shortcode": "BDAZw6tHoIb",
    "file": "01KS3CBXAHEW8GZDKYGJHQFH1W.json",
    "error": "no_json"
  },
  {
    "shortcode": "DW_TK7FiNLe",
    "file": "01KS3CQYJ9WMW0MHNRJ8288QHQ.json",
    "error": "no_json"
  },
  {
    "shortcode": "DW6XZBgiDS8",
    "file": "01KS3CQYJDHVZKPG09FZJ7XVDB.json",
    "error": "no_json"
  },
  {
    "shortcode": "CzJPRm5tPFx",
    "file": "01KS3CQYJGKZP9954ZSSGXC9GA.json",
    "error": "no_json"
  },
  {
    "shortcode": "DAgg5A7tU0g",
    "file": "01KS3CQYJKJXMYH1VFKKVV9Q82.json",
    "error": "no_json"
  },
  {
    "shortcode": "C3o-DWFIgD_",
    "file": "01KS3CQYJQZAPMQKRDFQ556GPT.json",
    "error": "no_json"
  },
  {
    "shortcode": "DGVEFWcNbqi",
    "file": "01KS3CQYJTEFH1GX76YKJ0WTE4.json",
    "error": "no_json"
  },
  {
    "shortcode": "C4nW6uRtDj_",
    "file": "01KS3CQYJX56A5GB2ZE9TNDF80.json",
    "error": "no_json"
  },
  {
    "shortcode": "Cz089F0Njdp",
    "file": "01KS3CQYK1EJNQ4RBR50BQ0P14.json",
    "error": "no_json"
  },
  {
    "shortcode": "DFxJZXDNBkW",
    "file": "01KS3CQYK4JTFQ2XFHY7XSCAAD.json",
    "error": "no_json"
  },
  {
    "shortcode": "C45aE9gtSGV",
    "file": "01KS3CQYK7GMB06M07GFND43T9.json",
    "error": "no_json"
  },
  {
    "shortcode": "C-agraWtSqX",
    "file": "01KS3CQYKA5BXM0X2XW06NMWYP.json",
    "error": "no_json"
  },
  {
    "shortcode": "C29k1X2IFeN",
    "file": "01KS3CQYKDT1SXTKVPGKFT24AD.json",
    "error": "no_json"
  },
  {
    "shortcode": "C2CYrdhOh4w",
    "file": "01KS3CQYKGYXKMS83BYJKSDNQT.json",
    "error": "no_json"
  },
  {
    "shortcode": "C9k3wzXtTVF",
    "file": "01KS3CQYKM60J6DB6P1JHEHH73.json",
    "error": "no_json"
  },
  {
    "shortcode": "DGDMoBuNnSV",
    "file": "01KS3CQYKP144Z8H387Y1Y9GS0.json",
    "error": "no_json"
  },
  {
    "shortcode": "DYUhMEaIaBj",
    "file": "01KS3CQYKSW8EYXYN01STQMAMX.json",
    "error": "no_json"
  },
  {
    "shortcode": "DYUN3RiILkv",
    "file": "01KS3CQYKWN8Y68B3XEPYTET6Z.json",
    "error": "no_json"
  },
  {
    "shortcode": "DYSVkJvIyC9",
    "file": "01KS3CQYKZNBFZSN84RSG1GB5B.json",
    "error": "no_json"
  },
  {
    "shortcode": "DXEd4jSiEjn",
    "file": "01KS3CQYM6GXGC3C289XADJYZZ.json",
    "error": "no_json"
  },
  {
    "shortcode": "DAQaQreNude",
    "file": "01KS3CQYM95TA1SVFSNSV3J2FJ.json",
    "error": "no_json"
  },
  {
    "shortcode": "DLLUBb6IUYi",
    "file": "01KS3CQYMCZXDFPZXTS7GF6HVV.json",
    "error": "no_json"
  },
  {
    "shortcode": "DG8-JPpNKdd",
    "file": "01KS3CQYMFT4PH4W1196F6DST8.json",
    "error": "no_json"
  },
  {
    "shortcode": "DGp7MwktyAx",
    "file": "01KS3CQYMJ5RM5Z7FT94KWFBJJ.json",
    "error": "no_json"
  },
  {
    "shortcode": "DA0JRxKtM1p",
    "file": "01KS3CQYMNF2T5NMZ1DPBJG81N.json",
    "error": "no_json"
  },
  {
    "shortcode": "B-XSleol9dL",
    "file": "01KS3EBN2HP0DQT6XKQR7EQDDR.json",
    "error": "no_json"
  },
  {
    "shortcode": "B91jWVCFbGS",
    "file": "01KS3EBN2N3HYMYGCYFQKSYX6N.json",
    "error": "no_json"
  },
  {
    "shortcode": "B9L1PwblUCW",
    "file": "01KS3EBN2TTGK1STKBMEE2YFJP.json",
    "error": "no_json"
  },
  {
    "shortcode": "B9eB4ibJqPe",
    "file": "01KS3EBN2ZBD9TJBTE5XCBS5W2.json",
    "error": "no_json"
  },
  {
    "shortcode": "C-SL2-xII66",
    "file": "01KS3EBN33HYF2QYTKG08974S9.json",
    "error": "no_json"
  },
  {
    "shortcode": "C-aPV0ko6lj",
    "file": "01KS3EETZHBMRY8NAEZ83YDEHX.json",
    "error": "no_json"
  },
  {
    "shortcode": "C-dZohOIX-y",
    "file": "01KS3EETZP763NH8AQTHDN92RW.json",
    "error": "no_json"
  },
  {
    "shortcode": "C-kvDklI0lo",
    "file": "01KS3EETZZ41Z6XQQPQBBVR96F.json",
    "error": "no_json"
  },
  {
    "shortcode": "C0MPeG4uTUI",
    "file": "01KS3EEV047JXF0X37TAGY6FH5.json",
    "error": "no_json"
  },
  {
    "shortcode": "DX_qeWDmh9J",
    "file": "01KS5PCAERAY0WYH0WN6AVHESC.json",
    "error": "no_json"
  },
  {
    "shortcode": "DX9TYFKE7WO",
    "file": "01KS5PCAETX85QMGTQW5BVX5M1.json",
    "error": "no_json"
  },
  {
    "shortcode": "DX7APMGE2_M",
    "file": "01KS5PCAEVEWFT5VKZNN29A5PZ.json",
    "error": "no_json"
  },
  {
    "shortcode": "DX60YwVk2mo",
    "file": "01KS5PCAEWAWXF4M2VM4EMC75Z.json",
    "error": "no_json"
  },
  {
    "shortcode": "DX4bYVHE_X-",
    "file": "01KS5PCAEXSM35BFKYXJWVM56T.json",
    "error": "no_json"
  },
  {
    "shortcode": "DX33QjaDUqf",
    "file": "01KS5PCAEYF3D9NA4TW0RXWTNV.json",
    "error": "no_json"
  },
  {
    "shortcode": "DX31OLOmufm",
    "file": "01KS5PCAEZDCNN9YDBWX870HPG.json",
    "error": "no_json"
  },
  {
    "shortcode": "DX1lNeBERdI",
    "file": "01KS5PCAF1C7SAJB7A7Z7Q1VX3.json",
    "error": "no_json"
  },
  {
    "shortcode": "DX1GIE2mkFX",
    "file": "01KS5PCAF2F4N20A2PCXBM9CK3.json",
    "error": "no_json"
  },
  {
    "shortcode": "DXyroUMGhec",
    "file": "01KS5PCAF31ZKJW0ECW30KBT5N.json",
    "error": "no_json"
  },
  {
    "shortcode": "DXw-jOhkZjC",
    "file": "01KS5PCAF4TVK46G5Q74V3X8XZ.json",
    "error": "no_json"
  },
  {
    "shortcode": "DXwb2X7CENo",
    "file": "01KS5PCAF5GXC1XF2RA9K2BG0S.json",
    "error": "no_json"
  },
  {
    "shortcode": "DXwKRPEDlfr",
    "file": "01KS5PCAF63XP5V6MA9XR2RBQE.json",
    "error": "no_json"
  },
  {
    "shortcode": "DXt99sgAX6Y",
    "file": "01KS5PCAF79TP81E6AJ7TG8478.json",
    "error": "no_json"
  },
  {
    "shortcode": "DXtKd57EftP",
    "file": "01KS5PCAF8GY14G1JRHCTNG20J.json",
    "error": "no_json"
  },
  {
    "shortcode": "DYmaOm-CRmG",
    "file": "01KS5PYQ85JY7CNGTN9QB92TAZ.json",
    "error": "no_json"
  },
  {
    "shortcode": "DYkgJQmEdqZ",
    "file": "01KS5PYQ87CHJZ1PVPRVYXMS05.json",
    "error": "no_json"
  },
  {
    "shortcode": "DYj0KFPjb5h",
    "file": "01KS5PYQ88T5AAR9PTC4NEWMPQ.json",
    "error": "no_json"
  },
  {
    "shortcode": "DYjxFTiFhpt",
    "file": "01KS5PYQ895NWPD596489WBDA0.json",
    "error": "no_json"
  },
  {
    "shortcode": "DYiCr1yufpQ",
    "file": "01KS5PYQ8A7WYSG74KFP9QTHZR.json",
    "error": "no_json"
  },
  {
    "shortcode": "DYhT7MwFnty",
    "file": "01KS5PYQ8C9W7XSGDHHDNRTFCF.json",
    "error": "no_json"
  },
  {
    "shortcode": "DYfCLAsDDGi",
    "file": "01KS5PYQ8DDJTYKT94C391JD82.json",
    "error": "no_json"
  },
  {
    "shortcode": "DYecnZXlYSu",
    "file": "01KS5PYQ8ENTHYZNKKYRXEGN4C.json",
    "error": "no_json"
  },
  {
    "shortcode": "DYc_szXAdDc",
    "file": "01KS5PYQ8FF3W8J1DESHZ1346C.json",
    "error": "no_json"
  },
  {
    "shortcode": "DYbeNxLIh7r",
    "file": "01KS5PYQ8G5MSR2MD02MH8HWP0.json",
    "error": "no_json"
  },
  {
    "shortcode": "DYZUCy0kjTx",
    "file": "01KS5PYQ8HNXJ7F87TS5N2B05Y.json",
    "error": "no_json"
  },
  {
    "shortcode": "DYXUhLQoe52",
    "file": "01KS5PYQ8JR9A9RKQKS8NNZP4M.json",
    "error": "no_json"
  },
  {
    "shortcode": "DYWpCuLDcAW",
    "file": "01KS5PYQ8K7RMB30T9JGZXV3A6.json",
    "error": "no_json"
  },
  {
    "shortcode": "DYWoq9YjH8q",
    "file": "01KS5PYQ8MCJ6XGCH1HMQ31W4R.json",
    "error": "no_json"
  },
  {
    "shortcode": "DYWn9hzjYhe",
    "file": "01KS5PYQ8N1M5W3F0YB4CMS04E.json",
    "error": "no_json"
  },
  {
    "shortcode": "DXzkeYyjdUb",
    "file": "01KS5PYQ8Q309WNT1A861446DB.json",
    "error": "no_json"
  },
  {
    "shortcode": "DXc6nXjCMLa",
    "file": "01KS5PYQ8R2CG7ARWF1V6NGZSJ.json",
    "error": "no_json"
  },
  {
    "shortcode": "DWzRYzqjc-L",
    "file": "01KS5PYQ8SBM9YZXHBK52VDYNP.json",
    "error": "no_json"
  },
  {
    "shortcode": "DWb2w60jdAY",
    "file": "01KS5PYQ8TEQSEY7D0ZERHXBEJ.json",
    "error": "no_json"
  },
  {
    "shortcode": "DWJzHH7DPwl",
    "file": "01KS5PYQ8VQ9EEJ8FZKFCM839Y.json",
    "error": "no_json"
  },
  {
    "shortcode": "DWHTU0qDSDh",
    "file": "01KS5PYQ8WE21HCTV91MB5CXGD.json",
    "error": "no_json"
  },
  {
    "shortcode": "DWHG8zREwPl",
    "file": "01KS5PYQ8XEVSVXX111K24JV17.json",
    "error": "no_json"
  },
  {
    "shortcode": "DVwE1fqjeoE",
    "file": "01KS5PYQ8YS2YNN2PFDKP2BBBY.json",
    "error": "no_json"
  },
  {
    "shortcode": "DVvj6u8FUZg",
    "file": "01KS5PYQ8ZSFG7JZ2DWZZ4Y8FT.json",
    "error": "no_json"
  },
  {
    "shortcode": "DVRXKGplejk",
    "file": "01KS5PYQ90QSYEQZ9T6N9EDTPB.json",
    "error": "no_json"
  },
  {
    "shortcode": "DVCIqF_jQbK",
    "file": "01KS5PYQ91RQ4SMSPZK6ZC7STQ.json",
    "error": "no_json"
  },
  {
    "shortcode": "DU6UivyDVQ5",
    "file": "01KS5PYQ92YKPP7Z5MZB8WWNX0.json",
    "error": "no_json"
  },
  {
    "shortcode": "DU3auXNjSAH",
    "file": "01KS5PYQ94HN08SWGBN06CZQT3.json",
    "error": "no_json"
  },
  {
    "shortcode": "DUYuWzmjQVQ",
    "file": "01KS5PYQ95GW4RYJC17YXEN8DP.json",
    "error": "no_json"
  },
  {
    "shortcode": "DTsJWGkjHuK",
    "file": "01KS5PYQ96B7YKQR089QC66RZG.json",
    "error": "no_json"
  },
  {
    "shortcode": "DXnevp3iK-_",
    "file": "01KS5QQ8DK6A5348ZWJ2XRPGCT.json",
    "error": "no_json"
  },
  {
    "shortcode": "DYkGdU_sZ31",
    "file": "01KS5QQ8DMY3N6Y0EW7SZR15BQ.json",
    "error": "no_json"
  },
  {
    "shortcode": "DXcDGDDjCtJ",
    "file": "01KS5QQ8DNVMRZSZGDDD1DYQZ5.json",
    "error": "no_json"
  },
  {
    "shortcode": "DXXCVvUDIta",
    "file": "01KS5QQ8DPFJQDTRB9FJ04QMQQ.json",
    "error": "no_json"
  },
  {
    "shortcode": "DXuUvIljNhq",
    "file": "01KS5QQ8DQC5C7TBJJDTDXKGMX.json",
    "error": "no_json"
  },
  {
    "shortcode": "DYSp_tzxsMp",
    "file": "01KS5QQ8DRFQ5BJFKSBM7W64VV.json",
    "error": "no_json"
  },
  {
    "shortcode": "DYFZ-qSMXoY",
    "file": "01KS5QQ8DT2XHE2EZ7V07NTAVM.json",
    "error": "no_json"
  },
  {
    "shortcode": "DYCL792sEZg",
    "file": "01KS5QQ8DV3H5CRTE18V5ZV9XS.json",
    "error": "no_json"
  },
  {
    "shortcode": "DX7L6hhxl7X",
    "file": "01KS5QQ8DW18E7D7J4QN2HRN98.json",
    "error": "no_json"
  },
  {
    "shortcode": "DX3GgvrowaY",
    "file": "01KS5QQ8DX7KJ1YFAR9JPYHXM7.json",
    "error": "no_json"
  },
  {
    "shortcode": "DX95GVeuMyp",
    "file": "01KS5QQ8DYCHJ5J9PZV2R5XAFK.json",
    "error": "no_json"
  },
  {
    "shortcode": "DXbW6HNDG_b",
    "file": "01KS5QQ8DZ1DBT1RTZFH3ZVX9T.json",
    "error": "no_json"
  },
  {
    "shortcode": "DXZSBKwjNwr",
    "file": "01KS5QQ8E0ABW30F125S9QP530.json",
    "error": "no_json"
  },
  {
    "shortcode": "DYkeED3uAXg",
    "file": "01KS5QQ8E1HBCXEXD2HRGD53SB.json",
    "error": "no_json"
  },
  {
    "shortcode": "DYl6VYqMRLN",
    "file": "01KS5QQ8E26552JYC32KPZVQJA.json",
    "error": "no_json"
  },
  {
    "shortcode": "DYhjysHiTsS",
    "file": "01KS5R47RDJ1V2TSB5EM7C05J0.json",
    "error": "no_json"
  },
  {
    "shortcode": "DYPipxvCVrt",
    "file": "01KS5R47RGDC3VECBF0KDKBDBV.json",
    "error": "no_json"
  },
  {
    "shortcode": "DYcNVQPFRdV",
    "file": "01KS5R47RJ83ZJ3FHKW27MQT6C.json",
    "error": "no_json"
  },
  {
    "shortcode": "DYhXXFzCMF4",
    "file": "01KS5R47RNXPYQSTFGTJF673JP.json",
    "error": "no_json"
  },
  {
    "shortcode": "DYRlM6HDJea",
    "file": "01KS5R47RQF2N5KD1H6TC31N2D.json",
    "error": "no_json"
  },
  {
    "shortcode": "DYAJZD1lVEN",
    "file": "01KS5R47RT32A1FCSNV94GBFGD.json",
    "error": "no_json"
  },
  {
    "shortcode": "DYFB2xhCCTz",
    "file": "01KS5R47RWX3WRM3TJT43BC2AE.json",
    "error": "no_json"
  },
  {
    "shortcode": "DYW8lLAlWBi",
    "file": "01KS5R47RZXKX2EA9Y62VZ7E93.json",
    "error": "no_json"
  },
  {
    "shortcode": "DXWuN04jrqs",
    "file": "01KS5R47S2GZBB7RH4PA2BAT3E.json",
    "error": "no_json"
  },
  {
    "shortcode": "DYkJMVAkrfR",
    "file": "01KS5R47S4EGFRBQHP9FFJBJSM.json",
    "error": "no_json"
  },
  {
    "shortcode": "DYO8d-fDYdN",
    "file": "01KS5R47S7VV314C7FDTXQS814.json",
    "error": "no_json"
  },
  {
    "shortcode": "DYPOH3-Enx3",
    "file": "01KS5R47S9Z251BC3RKZSS0FHE.json",
    "error": "no_json"
  },
  {
    "shortcode": "DYR0cj-m2AE",
    "file": "01KS5R47SC3SPNC6AVCX1A0SKC.json",
    "error": "no_json"
  },
  {
    "shortcode": "DYKExihklsJ",
    "file": "01KS5R47SECASTS5MGYY0RNZAR.json",
    "error": "no_json"
  },
  {
    "shortcode": "DYmTWzYFiKQ",
    "file": "01KS5R47SH4JJQGHBB3TEFFPA8.json",
    "error": "no_json"
  },
  {
    "shortcode": "DYcBJmAlPPa",
    "file": "01KS5VCPEPEGHJ7WP3N3R3D4VM.json",
    "error": "no_json"
  },
  {
    "shortcode": "DYcCtYvDd3L",
    "file": "01KS5VCPEW1AAF4AY711J8MGRA.json",
    "error": "no_json"
  },
  {
    "shortcode": "DYZF1OSCpQo",
    "file": "01KS5VCPF08ESARY8VEVMHHDGP.json",
    "error": "no_json"
  },
  {
    "shortcode": "DYewDs4jfcA",
    "file": "01KS5VCPF4VCCBCHCVD3Q6M6WM.json",
    "error": "no_json"
  },
  {
    "shortcode": "DYXaQk6mFWD",
    "file": "01KS5VCPF81EB6ZBWDHP52KZT4.json",
    "error": "no_json"
  },
  {
    "shortcode": "DYkHkm6kl4M",
    "file": "01KS5VCPFBW5SHD74AZGZR525B.json",
    "error": "no_json"
  },
  {
    "shortcode": "DYhSno-gTR4",
    "file": "01KS5VCPFF8RY8QZM02Z2XH3H3.json",
    "error": "no_json"
  },
  {
    "shortcode": "DYUlT9tGjXG",
    "file": "01KS5VCPFKQB63E8XSD11ENFFP.json",
    "error": "no_json"
  },
  {
    "shortcode": "DYmV1F2mYE5",
    "file": "01KS5VCPFQJEQ8VM7F1MBM96NS.json",
    "error": "no_json"
  },
  {
    "shortcode": "DHOdUpGtpNK",
    "file": "01KS5VCPFVVHMJCN15PEMVTMCA.json",
    "error": "no_json"
  },
  {
    "shortcode": "DJJzbe6sszd",
    "file": "01KS5VCPFYYW10C8SNXBYZ92VC.json",
    "error": "no_json"
  },
  {
    "shortcode": "DI8ll3BuJlP",
    "file": "01KS5VCPG28KMTZH8ZNPBCG4EG.json",
    "error": "no_json"
  },
  {
    "shortcode": "DI1FEFLAjmI",
    "file": "01KS5VCPG6MPK193NR72TYPKTP.json",
    "error": "no_json"
  },
  {
    "shortcode": "DI_Fxw5Mm3C",
    "file": "01KS5VCPGAE5PPV877GERCWAGD.json",
    "error": "no_json"
  },
  {
    "shortcode": "DJEMjK7NH0p",
    "file": "01KS5VCPGDRSQ0HK028KZFB5QS.json",
    "error": "no_json"
  },
  {
    "shortcode": "DIzDbZXp2T8",
    "file": "01KS5VCPGH6JW4F0PT48XAS36G.json",
    "error": "no_json"
  },
  {
    "shortcode": "DJHc3VuBMQe",
    "file": "01KS5VCPGNQG13NFJQJFKTXWR8.json",
    "error": "no_json"
  },
  {
    "shortcode": "DI4F0zJssUN",
    "file": "01KS5VCPGS470YNW39SW0J2EMN.json",
    "error": "no_json"
  },
  {
    "shortcode": "DJMfheeBywF",
    "file": "01KS5VCPGW69SRSE1NCZBX6CQD.json",
    "error": "no_json"
  },
  {
    "shortcode": "DJGpA6APMf-",
    "file": "01KS5VCPH0WW7Z23F651SVH8RJ.json",
    "error": "no_json"
  },
  {
    "shortcode": "DESKoJOtKHM",
    "file": "01KS5VCPH41R7ZHPSGQJZPXY11.json",
    "error": "no_json"
  },
  {
    "shortcode": "DDMYO6oI9SR",
    "file": "01KS5VCPH81Y5NYWGASGGW8YR5.json",
    "error": "no_json"
  },
  {
    "shortcode": "DGoP-afIJfc",
    "file": "01KS5VCPHBDJ1QAH0A41ZEPKQ1.json",
    "error": "no_json"
  },
  {
    "shortcode": "DARXS4GICq2",
    "file": "01KS5VCPHFGXNAMVP7R6Y0DW7R.json",
    "error": "no_json"
  },
  {
    "shortcode": "DGlu_wTPDat",
    "file": "01KS5VCPHKD6GWWDA02ENRSVXD.json",
    "error": "no_json"
  },
  {
    "shortcode": "DDcf4juINp6",
    "file": "01KS5VCPHQ2TV08H27K3XR75ZC.json",
    "error": "no_json"
  },
  {
    "shortcode": "DAMUHbmII_6",
    "file": "01KS5VCPHV463F6X3Y1TYPFW99.json",
    "error": "no_json"
  },
  {
    "shortcode": "DBzJJxmo9Mo",
    "file": "01KS5VCPHYPY3575PEAHWZSAXC.json",
    "error": "no_json"
  },
  {
    "shortcode": "DGYR6aZt4rJ",
    "file": "01KS5VCPJ2V9MY82SR8Q63W68Y.json",
    "error": "no_json"
  },
  {
    "shortcode": "DGQ0TdSNjTA",
    "file": "01KS5VCPJ6JT8CX89AKZH5TB7E.json",
    "error": "no_json"
  },
  {
    "shortcode": "DCHbSyONS-o",
    "file": "01KS5VCPJ9413Z7E0H5NM0NGWZ.json",
    "error": "no_json"
  },
  {
    "shortcode": "DCB3Uj7Namb",
    "file": "01KS5VCPJDJ0K3YF0MFPRK1FRM.json",
    "error": "no_json"
  },
  {
    "shortcode": "DCCMO42N6T8",
    "file": "01KS5VCPJNQRTAZWTH7YG69EN5.json",
    "error": "no_json"
  },
  {
    "shortcode": "DCM1YBdO6kU",
    "file": "01KS5VCPJSJCAEZ15D2FCGJJQJ.json",
    "error": "no_json"
  },
  {
    "shortcode": "DCPSQvftxLY",
    "file": "01KS5VCPJWP6F8KJKBJ5E4885M.json",
    "error": "no_json"
  },
  {
    "shortcode": "DCCZ4lkutrP",
    "file": "01KS5VCPK064ASND884SRTWSD9.json",
    "error": "no_json"
  },
  {
    "shortcode": "DCEcQHcNk9Z",
    "file": "01KS5VCPK4F1BMWA57J4HDFAVA.json",
    "error": "no_json"
  },
  {
    "shortcode": "DCe1DOWuzU1",
    "file": "01KS5VCPK7N033RV57P7C8EEDM.json",
    "error": "no_json"
  },
  {
    "shortcode": "DCMzu-NOgGh",
    "file": "01KS5VCPKBAT1FVVNJMTK6PWC2.json",
    "error": "no_json"
  },
  {
    "shortcode": "DYhVXYdDmMs",
    "file": "01KS5VCPMM4CZPZP8BWGQMKX2S.json",
    "error": "no_json"
  },
  {
    "shortcode": "DYerHNrlax-",
    "file": "01KS5VCPMRBMK7EVP2YHYG22F5.json",
    "error": "no_json"
  },
  {
    "shortcode": "DYbyzHgFS_Y",
    "file": "01KS5VCPMWBTV29C762ZT4CY1Y.json",
    "error": "no_json"
  },
  {
    "shortcode": "DYUClVACEyq",
    "file": "01KS5VCPMZNVVVPWBDR8JXVYHJ.json",
    "error": "no_json"
  },
  {
    "shortcode": "DYMU0oFjg5f",
    "file": "01KS5VCPN3S2HQ97MF6REN3FCM.json",
    "error": "no_json"
  },
  {
    "shortcode": "DYHfBx0EnK5",
    "file": "01KS5VCPN7M1TGN542T72BMG6C.json",
    "error": "no_json"
  },
  {
    "shortcode": "DYE2-R0DC6c",
    "file": "01KS5VCPNB7Y3HEX7GXGCAH1SE.json",
    "error": "no_json"
  },
  {
    "shortcode": "DYCCTOFGheK",
    "file": "01KS5VCPNE6HMXJHT3AXM70A5M.json",
    "error": "no_json"
  },
  {
    "shortcode": "DYedLFSiGrW",
    "file": "01KS5VCPNHHSHPBQDG7WXR8PAJ.json",
    "error": "no_json"
  },
  {
    "shortcode": "DYW8lLAlWBi",
    "file": "01KS5VCPNNWSXYYDK56EH155HH.json",
    "error": "no_json"
  },
  {
    "shortcode": "DXw-I85gBIN",
    "file": "01KS5XZ1X8PPG2X7R5JQC42EJ5.json",
    "error": "no_json"
  },
  {
    "shortcode": "DXw-FfhANoE",
    "file": "01KS5XZ20CE6RHXQAQPDH4AFAX.json",
    "error": "no_json"
  },
  {
    "shortcode": "DXw-ApwAFhu",
    "file": "01KS5XZ23GRHEM3E2MSH4DMDZS.json",
    "error": "no_json"
  },
  {
    "shortcode": "DYkCRVyALeA",
    "file": "01KS5XZ26MX9G8FGVSQE8Z5379.json",
    "error": "no_json"
  },
  {
    "shortcode": "DYb_O2SAGes",
    "file": "01KS5XZ29RAV4RRXG07HN7JVAX.json",
    "error": "no_json"
  },
  {
    "shortcode": "DYO5hA8AG5s",
    "file": "01KS5XZ2CW0GB6KC9QA0MZ17QK.json",
    "error": "no_json"
  },
  {
    "shortcode": "DYNOyPiAFYX",
    "file": "01KS5XZ2G0F3F55Z488YAGVDCK.json",
    "error": "no_json"
  },
  {
    "shortcode": "DYMqn2aDOoi",
    "file": "01KS5XZ2K4SQWW7FE4N1EE043E.json",
    "error": "no_json"
  },
  {
    "shortcode": "DYhZiQ5DGus",
    "file": "01KS5XZ2P842N4FHZD8YFYTC66.json",
    "error": "no_json"
  },
  {
    "shortcode": "DYSU4-JztAw",
    "file": "01KS5XZ2SCVPVTX363SN6FCCW8.json",
    "error": "no_json"
  },
  {
    "shortcode": "DYXXx5YTqrd",
    "file": "01KS5XZ2WGVBHXF4W6305FATZY.json",
    "error": "no_json"
  },
  {
    "shortcode": "DYhrpFVztUN",
    "file": "01KS5XZ2ZMDS3AR0RGXJVZ9CJD.json",
    "error": "no_json"
  },
  {
    "shortcode": "DYmjZIxI3cS",
    "file": "01KS5Y548033M33YA35B44FS7F.json",
    "error": "no_json"
  },
  {
    "shortcode": "DYmg8rwoM-v",
    "file": "01KS5Y54B425TMGDMFGS8KXM40.json",
    "error": "no_json"
  },
  {
    "shortcode": "DYmeutzo_Vp",
    "file": "01KS5Y54E8X64DG8P4FQJAWK0K.json",
    "error": "no_json"
  },
  {
    "shortcode": "DYkDCyqs2Dq",
    "file": "01KS5Y54HC68G769HJDNDGZG35.json",
    "error": "no_json"
  },
  {
    "shortcode": "DYhklLfDGVq",
    "file": "01KS5Y54MGVH20N8GAWV07492Q.json",
    "error": "no_json"
  },
  {
    "shortcode": "DYmPY1ko5tY",
    "file": "01KS5Y54QM9V82KQ2PDF6PT9FA.json",
    "error": "no_json"
  },
  {
    "shortcode": "DYhcrGdDD_k",
    "file": "01KS5Y54TRBT1BNTFHA6R2YECX.json",
    "error": "no_json"
  },
  {
    "shortcode": "DYfgrDAuGXN",
    "file": "01KS5Y54XWPKEE1CSNH4HPSN17.json",
    "error": "no_json"
  },
  {
    "shortcode": "DYe3N_yMsxS",
    "file": "01KS5Y5510GBG26VPMV7RCG2V0.json",
    "error": "no_json"
  },
  {
    "shortcode": "DYepv6jjHD9",
    "file": "01KS5Y5544CQV4NM7KKTMSJ8CT.json",
    "error": "no_json"
  },
  {
    "shortcode": "DYcZ6EEsQ18",
    "file": "01KS5Y5578RBKS0KJDVMXWWDYA.json",
    "error": "no_json"
  },
  {
    "shortcode": "DYkC-tTsi9O",
    "file": "01KS5Y55AC5JN5FKEC912FY4XT.json",
    "error": "no_json"
  },
  {
    "shortcode": "DYj72tQCMy7",
    "file": "01KS5W2DY3QBYW1M9Q34D0YJYR.json",
    "error": "no_json"
  },
  {
    "shortcode": "DYcQ8gCsB9s",
    "file": "01KS5W2DY8RYRAR1QNHTS8VH2G.json",
    "error": "no_json"
  },
  {
    "shortcode": "DYZglTRqj86",
    "file": "01KS5W2DYC9AZXCXY4RW8DW509.json",
    "error": "no_json"
  },
  {
    "shortcode": "DYhLjZcIpsz",
    "file": "01KS5W2DYGAN5F6F99GWCNFDT4.json",
    "error": "no_json"
  },
  {
    "shortcode": "DYXpoI0IWa_",
    "file": "01KS5W2DYMP7T2Q11GR66QN5GC.json",
    "error": "no_json"
  },
  {
    "shortcode": "DYXpkOOoo3a",
    "file": "01KS5W2DYRHJ092KRCKY3YXSHW.json",
    "error": "no_json"
  },
  {
    "shortcode": "DYfEQ_nMhnK",
    "file": "01KS5W2DYVNK5QMMRQX873SE11.json",
    "error": "no_json"
  },
  {
    "shortcode": "DYkRDOqtQsR",
    "file": "01KS5W2DYZR6DT76XTT1M68E59.json",
    "error": "no_json"
  },
  {
    "shortcode": "DYXPQ7FILkD",
    "file": "01KS5W2DZ33D975HV1B7VD36Y6.json",
    "error": "no_json"
  },
  {
    "shortcode": "DYXOtrUIyjJ",
    "file": "01KS5W2DZ7SZ2E22R18GVH6QP6.json",
    "error": "no_json"
  },
  {
    "shortcode": "DYXPIn7Iy8w",
    "file": "01KS5W2DZBCHSH3TA7FWE0WG5G.json",
    "error": "no_json"
  },
  {
    "shortcode": "DYXOqxuoG6K",
    "file": "01KS5W2DZEX0BHFZ69DWAH71T9.json",
    "error": "no_json"
  },
  {
    "shortcode": "DYXpXxpIEUD",
    "file": "01KSB647PEERHEFAH7JEAKWK40.json",
    "error": "no_json"
  },
  {
    "shortcode": "DYXQFl2IGdz",
    "file": "01KSB647PHNXVPWADR6Y6835JE.json",
    "error": "no_json"
  },
  {
    "shortcode": "DYXC4XDzPu6",
    "file": "01KSB647PMV8W3BWV4F0MXHN5H.json",
    "error": "no_json"
  },
  {
    "shortcode": "DYXCeOgTOMd",
    "file": "01KSB647PQA2ETA5AFQBKN4J3E.json",
    "error": "no_json"
  },
  {
    "shortcode": "DYXAVZqN6Bz",
    "file": "01KSB647PTXDDFN4FCKRKZS5H4.json",
    "error": "no_json"
  },
  {
    "shortcode": "DYW0EaAOe-P",
    "file": "01KSB647PXKR8S4B04FQ260H4Z.json",
    "error": "no_json"
  },
  {
    "shortcode": "DYTKbBTIP_I",
    "file": "01KSB647Q0P17VSHSJ9QR21XGS.json",
    "error": "no_json"
  },
  {
    "shortcode": "DYTKIYsogLg",
    "file": "01KSB647Q3V89CY9KC9NB0E27D.json",
    "error": "no_json"
  },
  {
    "shortcode": "DYSI4sKiIGA",
    "file": "01KSB647Q6B8ZAWHMSX53E305N.json",
    "error": "no_json"
  },
  {
    "shortcode": "DYSA8kyoZfY",
    "file": "01KSB647Q940N6M934DB73C9VE.json",
    "error": "no_json"
  },
  {
    "shortcode": "DYR5kPIIrY2",
    "file": "01KSB647QDR50JBC58J0JDAD55.json",
    "error": "no_json"
  },
  {
    "shortcode": "DYJ5X-YtGD2",
    "file": "01KSB647QGHWY3CMPK00R2F6X3.json",
    "error": "no_json"
  },
  {
    "shortcode": "DYHpyA4CJ5I",
    "file": "01KSB647QKW9262PEJCKJAXNNS.json",
    "error": "no_json"
  }
]