{
  "schema_version": 1,
  "generated_at": "2026-05-24T00:00:00Z",
  "corpus_baseline": 0.54,
  "total_obs": 2770,
  "obs_with_text_overlay": 409,
  "overlay_presence_table": [
    {
      "overlay_presence": "has_overlay",
      "count": 409,
      "high_engagement_rate": 0.496,
      "avg_engagement": 0.664,
      "lift_vs_baseline": -0.044
    },
    {
      "overlay_presence": "no_overlay",
      "count": 2361,
      "high_engagement_rate": 0.23,
      "avg_engagement": 0.359,
      "lift_vs_baseline": -0.31
    }
  ],
  "overlay_language_table": [
    {
      "overlay_language": "spanish",
      "count": 3,
      "high_engagement_rate": 1.0,
      "avg_engagement": 1.0,
      "lift_vs_baseline": 0.46,
      "top_sector": "f_and_b"
    },
    {
      "overlay_language": "latin",
      "count": 2,
      "high_engagement_rate": 1.0,
      "avg_engagement": 1.0,
      "lift_vs_baseline": 0.46,
      "top_sector": "f_and_b"
    },
    {
      "overlay_language": "handle",
      "count": 1,
      "high_engagement_rate": 1.0,
      "avg_engagement": 1.0,
      "lift_vs_baseline": 0.46,
      "top_sector": "f_and_b"
    },
    {
      "overlay_language": "english",
      "count": 87,
      "high_engagement_rate": 0.736,
      "avg_engagement": 0.856,
      "lift_vs_baseline": 0.196,
      "top_sector": "f_and_b"
    },
    {
      "overlay_language": "arabic",
      "count": 283,
      "high_engagement_rate": 0.431,
      "avg_engagement": 0.608,
      "lift_vs_baseline": -0.109,
      "top_sector": "f_and_b"
    },
    {
      "overlay_language": "bilingual",
      "count": 32,
      "high_engagement_rate": 0.344,
      "avg_engagement": 0.578,
      "lift_vs_baseline": -0.196,
      "top_sector": "f_and_b"
    },
    {
      "overlay_language": "username_only",
      "count": 1,
      "high_engagement_rate": 0.0,
      "avg_engagement": 0.5,
      "lift_vs_baseline": -0.54,
      "top_sector": "f_and_b"
    }
  ],
  "overlay_content_type_table": [
    {
      "overlay_type": "brand_identity",
      "count": 92,
      "high_engagement_rate": 0.63,
      "lift_vs_baseline": 0.09
    },
    {
      "overlay_type": "occasion_title",
      "count": 33,
      "high_engagement_rate": 0.606,
      "lift_vs_baseline": 0.066
    },
    {
      "overlay_type": "storytelling",
      "count": 5,
      "high_engagement_rate": 0.6,
      "lift_vs_baseline": 0.06
    },
    {
      "overlay_type": "price_offer",
      "count": 30,
      "high_engagement_rate": 0.533,
      "lift_vs_baseline": -0.007
    },
    {
      "overlay_type": "product_name",
      "count": 71,
      "high_engagement_rate": 0.451,
      "lift_vs_baseline": -0.089
    },
    {
      "overlay_type": "trivia_question",
      "count": 27,
      "high_engagement_rate": 0.444,
      "lift_vs_baseline": -0.096
    },
    {
      "overlay_type": "other",
      "count": 143,
      "high_engagement_rate": 0.42,
      "lift_vs_baseline": -0.12
    },
    {
      "overlay_type": "cta_overlay",
      "count": 8,
      "high_engagement_rate": 0.25,
      "lift_vs_baseline": -0.29
    }
  ],
  "language_by_occasion": [
    {
      "language": "arabic",
      "occasion": "winter_seasonal",
      "count": 2,
      "high_eng_rate": 1.0,
      "lift": 0.46
    },
    {
      "language": "arabic",
      "occasion": "eid_al_fitr",
      "count": 5,
      "high_eng_rate": 1.0,
      "lift": 0.46
    },
    {
      "language": "arabic",
      "occasion": "vision_2030",
      "count": 2,
      "high_eng_rate": 1.0,
      "lift": 0.46
    },
    {
      "language": "english",
      "occasion": "winter_seasonal",
      "count": 2,
      "high_eng_rate": 1.0,
      "lift": 0.46
    },
    {
      "language": "english",
      "occasion": "summer_campaign",
      "count": 2,
      "high_eng_rate": 1.0,
      "lift": 0.46
    },
    {
      "language": "english",
      "occasion": "eid_al_fitr",
      "count": 2,
      "high_eng_rate": 1.0,
      "lift": 0.46
    },
    {
      "language": "spanish",
      "occasion": "evergreen",
      "count": 3,
      "high_eng_rate": 1.0,
      "lift": 0.46
    },
    {
      "language": "arabic",
      "occasion": "national_day",
      "count": 8,
      "high_eng_rate": 0.875,
      "lift": 0.335
    },
    {
      "language": "arabic",
      "occasion": "ramadan",
      "count": 18,
      "high_eng_rate": 0.778,
      "lift": 0.238
    },
    {
      "language": "arabic",
      "occasion": "graduation_season",
      "count": 4,
      "high_eng_rate": 0.75,
      "lift": 0.21
    },
    {
      "language": "english",
      "occasion": "evergreen",
      "count": 77,
      "high_eng_rate": 0.74,
      "lift": 0.2
    },
    {
      "language": "arabic",
      "occasion": "founding_day",
      "count": 3,
      "high_eng_rate": 0.667,
      "lift": 0.127
    },
    {
      "language": "arabic",
      "occasion": "summer_campaign",
      "count": 5,
      "high_eng_rate": 0.6,
      "lift": 0.06
    },
    {
      "language": "arabic",
      "occasion": "brand_campaign",
      "count": 13,
      "high_eng_rate": 0.462,
      "lift": -0.078
    },
    {
      "language": "arabic",
      "occasion": "evergreen",
      "count": 201,
      "high_eng_rate": 0.378,
      "lift": -0.162
    },
    {
      "language": "bilingual",
      "occasion": "evergreen",
      "count": 30,
      "high_eng_rate": 0.333,
      "lift": -0.207
    },
    {
      "language": "arabic",
      "occasion": "eid_al_adha",
      "count": 8,
      "high_eng_rate": 0.125,
      "lift": -0.415
    },
    {
      "language": "arabic",
      "occasion": "sporting_event",
      "count": 11,
      "high_eng_rate": 0.091,
      "lift": -0.449
    },
    {
      "language": "arabic",
      "occasion": "national_sports_day",
      "count": 3,
      "high_eng_rate": 0.0,
      "lift": -0.54
    },
    {
      "language": "english",
      "occasion": "ramadan",
      "count": 3,
      "high_eng_rate": 0.0,
      "lift": -0.54
    }
  ],
  "agency_rules": [
    "Add text overlays — they lift engagement across corpus",
    "Best overlay language: 'spanish' (100%) — default to this for visual text"
  ],
  "key_findings": [
    "Text overlay HELPS engagement: with_overlay=49% vs without=23% (+26pp)",
    "Best overlay language: 'spanish' = 100% (n=3)",
    "Best overlay type: 'brand_identity' = 63% (n=92)",
    "Worst overlay type: 'cta_overlay' = 25% — use sparingly"
  ]
}