{
 "_meta": {
  "built": "2026-06-11",
  "files": 1002,
  "canonical_groups": 985,
  "alias_merge_groups": 13,
  "near_duplicate_stems": 6,
  "rule": "READ via canonical slug; alias slugs resolve here; no files were moved"
 },
 "prefix_aliases": {
  "food": "f_and_b",
  "food_beverage": "f_and_b",
  "fnb": "f_and_b",
  "beauty_personal_care": "beauty",
  "retail_lifestyle": "retail",
  "ecommerce": "retail",
  "healthcare": "health",
  "wellness": "health"
 },
 "alias_merges": {
  "f_and_b_beverage": [
   "f_and_b_beverage",
   "food_beverage"
  ],
  "f_and_b_brand_promotion": [
   "f_and_b_brand_promotion",
   "fnb_brand_promotion"
  ],
  "f_and_b_catering": [
   "f_and_b_catering",
   "food_catering"
  ],
  "f_and_b_engagement": [
   "f_and_b_engagement",
   "fnb_engagement"
  ],
  "f_and_b_menu_post": [
   "f_and_b_menu_post",
   "food_menu_post"
  ],
  "f_and_b_ordering": [
   "f_and_b_ordering",
   "food_ordering"
  ],
  "f_and_b_product_launch": [
   "f_and_b_product_launch",
   "fnb_product_launch",
   "food_product_launch"
  ],
  "f_and_b_promo": [
   "f_and_b_promo",
   "food_beverage_promo",
   "food_promo"
  ],
  "f_and_b_promotion": [
   "f_and_b_promotion",
   "food_beverage_promotion",
   "food_promotion"
  ],
  "f_and_b_promotional": [
   "f_and_b_promotional",
   "food_beverage_promotional",
   "food_promotional"
  ],
  "f_and_b_recommendation": [
   "f_and_b_recommendation",
   "food_recommendation"
  ],
  "f_and_b_discount": [
   "food_beverage_discount",
   "food_discount"
  ],
  "f_and_b_recommendation_request": [
   "food_beverage_recommendation_request",
   "food_recommendation_request"
  ]
 },
 "near_duplicate_candidates": {
  "cafe_brand": [
   "cafe_brand",
   "cafe_brand_content"
  ],
  "f_and_b_craving": [
   "f_and_b_craving",
   "f_and_b_craving_content"
  ],
  "gamification": [
   "gamification",
   "gamification_content"
  ],
  "giveaway_contest": [
   "giveaway_contest",
   "giveaway_contest_post"
  ],
  "holiday_seasonal": [
   "holiday_seasonal",
   "holiday_seasonal_content"
  ],
  "interactive_question": [
   "interactive_question",
   "interactive_question_post"
  ]
 }
}